.codecov.yml
.coveragerc
.cspell.json
.editorconfig
.gitattributes
.gitignore
.readthedocs.yml
CONTRIBUTING.rst
LICENSE.rst
MANIFEST.in
Procfile
README.rst
app.json
package-lock.json
package.json
pyproject.toml
requirements.txt
runtime.txt
setup.cfg
setup.py
tox.ini
update-ui.sh
.github/ISSUE_TEMPLATE/bug.md
.github/ISSUE_TEMPLATE/feature.md
.github/PULL_REQUEST_TEMPLATE/general.md
.github/actions/install/action.yml
.github/workflows/publish.yml
.github/workflows/review.yml
docs/Makefile
docs/changelog.rst
docs/conf.py
docs/contributing.rst
docs/custom_spec.rst
docs/custom_ui.rst
docs/drf_yasg.rst
docs/index.rst
docs/license.rst
docs/make.bat
docs/openapi.rst
docs/readme.rst
docs/rendering.rst
docs/security.rst
docs/settings.rst
docs/_static/.gitignore
docs/_static/css/style.css
docs/_templates/.gitignore
docs/_templates/layout.html
requirements/base.txt
requirements/ci.txt
requirements/dev.txt
requirements/docs.txt
requirements/heroku.txt
requirements/lint.txt
requirements/publish.txt
requirements/test.txt
requirements/testproj.txt
requirements/tox.txt
requirements/validation.txt
screenshots/redoc-nested-response.png
screenshots/swagger-ui-list.png
screenshots/swagger-ui-models.png
src/djrf_yasg.egg-info/PKG-INFO
src/djrf_yasg.egg-info/SOURCES.txt
src/djrf_yasg.egg-info/dependency_links.txt
src/djrf_yasg.egg-info/requires.txt
src/djrf_yasg.egg-info/top_level.txt
src/drf_yasg/__init__.py
src/drf_yasg/app_settings.py
src/drf_yasg/codecs.py
src/drf_yasg/errors.py
src/drf_yasg/generators.py
src/drf_yasg/middleware.py
src/drf_yasg/openapi.py
src/drf_yasg/renderers.py
src/drf_yasg/utils.py
src/drf_yasg/views.py
src/drf_yasg/inspectors/__init__.py
src/drf_yasg/inspectors/base.py
src/drf_yasg/inspectors/field.py
src/drf_yasg/inspectors/query.py
src/drf_yasg/inspectors/view.py
src/drf_yasg/management/__init__.py
src/drf_yasg/management/commands/__init__.py
src/drf_yasg/management/commands/generate_swagger.py
src/drf_yasg/static/drf-yasg/README
src/drf_yasg/static/drf-yasg/immutable.js
src/drf_yasg/static/drf-yasg/immutable.min.js
src/drf_yasg/static/drf-yasg/insQ.js
src/drf_yasg/static/drf-yasg/insQ.min.js
src/drf_yasg/static/drf-yasg/redoc-init.js
