Metadata-Version: 2.1
Name: djrf-yasg
Version: 2.33.0
Summary: Automated generation of real Swagger/OpenAPI 2.0 schemas from Django Rest Framework code.
Home-page: https://github.com/mowarlee/drf-yasg
Author: Mowar Lee
Author-email: leemowar@gmail.com
License: BSD License
Keywords: drf django dj-rest-framework schema swagger openapi codegen swagger-codegen documentation drf-yasg drf-openapi
Classifier: Intended Audience :: Developers
Classifier: License :: OSI Approved :: BSD License
Classifier: Development Status :: 5 - Production/Stable
Classifier: Operating System :: OS Independent
Classifier: Environment :: Web Environment
Classifier: Topic :: Documentation
Classifier: Topic :: Software Development :: Code Generators
Classifier: Programming Language :: Python
Classifier: Programming Language :: Python :: 3
Classifier: Programming Language :: Python :: 3.6
Classifier: Programming Language :: Python :: 3.7
Classifier: Programming Language :: Python :: 3.8
Classifier: Programming Language :: Python :: 3.9
Classifier: Programming Language :: Python :: 3.10
Classifier: Programming Language :: Python :: 3.11
Classifier: Framework :: Django
Classifier: Framework :: Django :: 2.2
Classifier: Framework :: Django :: 3.0
Classifier: Framework :: Django :: 3.1
Classifier: Framework :: Django :: 3.2
Classifier: Framework :: Django :: 4.0
Classifier: Framework :: Django :: 4.1
Requires-Python: >=3.6
Provides-Extra: validation
Provides-Extra: coreapi
License-File: LICENSE.rst
